odoo/addons/base_export_anonymize/README.rst
odoo/addons/base_export_anonymize/__init__.py
odoo/addons/base_export_anonymize/__manifest__.py
odoo/addons/base_export_anonymize/data/ir_config_parameter.xml
odoo/addons/base_export_anonymize/i18n/base_export_anonymize.pot
odoo/addons/base_export_anonymize/i18n/it.po
odoo/addons/base_export_anonymize/models/__init__.py
odoo/addons/base_export_anonymize/models/base.py
odoo/addons/base_export_anonymize/models/ir_model_fields.py
odoo/addons/base_export_anonymize/models/ir_model_fields_export_anonymize.py
odoo/addons/base_export_anonymize/readme/CONTRIBUTORS.md
odoo/addons/base_export_anonymize/readme/DESCRIPTION.md
odoo/addons/base_export_anonymize/readme/USAGE.md
odoo/addons/base_export_anonymize/security/groups.xml
odoo/addons/base_export_anonymize/security/ir_model_fields_export_anonymize.xml
odoo/addons/base_export_anonymize/static/description/icon.png
odoo/addons/base_export_anonymize/static/description/index.html
odoo/addons/base_export_anonymize/views/ir_model_fields.xml
odoo/addons/base_export_anonymize/views/ir_model_fields_export_anonymize.xml
odoo_addon_base_export_anonymize-18.0.1.0.0.3.dist-info/METADATA
odoo_addon_base_export_anonymize-18.0.1.0.0.3.dist-info/WHEEL
odoo_addon_base_export_anonymize-18.0.1.0.0.3.dist-info/top_level.txt
odoo_addon_base_export_anonymize-18.0.1.0.0.3.dist-info/RECORD
