Metadata-Version: 2.1
Name: odoo-addon-base_export_anonymize
Version: 18.0.1.0.0.3
Requires-Python: >=3.10
Requires-Dist: odoo==18.0.*
Summary: Anonymize certain fields for a group of users when exporting them directly or via relational fields.
Home-page: https://github.com/OCA/data-protection
License: AGPL-3
Author: ACSONE SA/NV, Odoo Community Association (OCA)
Author-email: support@odoo-community.org
Classifier: Programming Language :: Python
Classifier: Framework :: Odoo
Classifier: Framework :: Odoo :: 18.0
Classifier: License :: OSI Approved :: GNU Affero General Public License v3
